<?xml version="1.0" encoding="UTF-8"?>
<!DOCTYPE plist PUBLIC "-//Apple//DTD PLIST 1.0//EN" "http://www.apple.com/DTDs/PropertyList-1.0.dtd"/>

<plist version="1.0">
    <dict>
        <key>ROOT</key>
        <array>
            <dict>
                <key>id</key>
                <string>104</string>
                <key>className</key>
                <string>PTModelSprite</string>
                <key>Name</key>
                <dict>
                    <key>value</key>
                    <string>5thblue</string>
                </dict>
                <key>pos</key>
                <string>{1632.00,132.00}</string>
                <key>offset</key>
                <string>{1.00,1.00}</string>
                <key>size</key>
                <string>{97.00,97.00}</string>
                <key>sourceSize</key>
                <string>{100.00,100.00}</string>
                <key>sourceRect</key>
                <string>{{1.00,1.00},{97.00,97.00}}</string>
            </dict>
            <dict>
                <key>id</key>
                <string>122</string>
                <key>className</key>
                <string>PTModelSprite</string>
                <key>Name</key>
                <dict>
                    <key>value</key>
                    <string>Ski_trail_rating_symbol_red_circle</string>
                </dict>
                <key>pos</key>
                <string>{1733.00,132.00}</string>
                <key>offset</key>
                <string>{6.00,6.00}</string>
                <key>size</key>
                <string>{88.00,88.00}</string>
                <key>sourceSize</key>
                <string>{100.00,100.00}</string>
                <key>sourceRect</key>
                <string>{{6.00,6.00},{88.00,88.00}}</string>
            </dict>
            <dict>
                <key>id</key>
                <string>141</string>
                <key>className</key>
                <string>PTModelSprite</string>
                <key>Name</key>
                <dict>
                    <key>value</key>
                    <string>redsquare</string>
                </dict>
                <key>pos</key>
                <string>{0.00,1019.00}</string>
                <key>offset</key>
                <string>{0.00,0.00}</string>
                <key>size</key>
                <string>{512.00,512.00}</string>
                <key>sourceSize</key>
                <string>{512.00,512.00}</string>
                <key>sourceRect</key>
                <string>{{0.00,0.00},{512.00,512.00}}</string>
            </dict>
            <dict>
                <key>id</key>
                <string>153</string>
                <key>className</key>
                <string>PTModelSprite</string>
                <key>Name</key>
                <dict>
                    <key>value</key>
                    <string>redsquare small</string>
                </dict>
                <key>pos</key>
                <string>{1896.00,0.00}</string>
                <key>offset</key>
                <string>{0.00,0.00}</string>
                <key>size</key>
                <string>{100.00,100.00}</string>
                <key>sourceSize</key>
                <string>{100.00,100.00}</string>
                <key>sourceRect</key>
                <string>{{0.00,0.00},{100.00,100.00}}</string>
            </dict>
            <dict>
                <key>id</key>
                <string>238</string>
                <key>className</key>
                <string>PTModelSprite</string>
                <key>Name</key>
                <dict>
                    <key>value</key>
                    <string>player</string>
                </dict>
                <key>pos</key>
                <string>{1923.00,233.00}</string>
                <key>offset</key>
                <string>{0.00,0.00}</string>
                <key>size</key>
                <string>{30.00,30.00}</string>
                <key>sourceSize</key>
                <string>{30.00,30.00}</string>
                <key>sourceRect</key>
                <string>{{0.00,0.00},{30.00,30.00}}</string>
            </dict>
            <dict>
                <key>id</key>
                <string>289</string>
                <key>className</key>
                <string>PTModelSprite</string>
                <key>Name</key>
                <dict>
                    <key>value</key>
                    <string>player</string>
                </dict>
                <key>pos</key>
                <string>{1889.00,233.00}</string>
                <key>offset</key>
                <string>{0.00,0.00}</string>
                <key>size</key>
                <string>{30.00,30.00}</string>
                <key>sourceSize</key>
                <string>{30.00,30.00}</string>
                <key>sourceRect</key>
                <string>{{0.00,0.00},{30.00,30.00}}</string>
            </dict>
            <dict>
                <key>id</key>
                <string>674</string>
                <key>className</key>
                <string>PTModelSprite</string>
                <key>Name</key>
                <dict>
                    <key>value</key>
                    <string>coin action</string>
                </dict>
                <key>pos</key>
                <string>{2040.00,4.00}</string>
                <key>offset</key>
                <string>{30.00,30.00}</string>
                <key>size</key>
                <string>{0.00,0.00}</string>
                <key>sourceSize</key>
                <string>{30.00,30.00}</string>
                <key>sourceRect</key>
                <string>{{30.00,30.00},{0.00,0.00}}</string>
            </dict>
            <dict>
                <key>id</key>
                <string>689</string>
                <key>className</key>
                <string>PTModelSprite</string>
                <key>Name</key>
                <dict>
                    <key>value</key>
                    <string>background</string>
                </dict>
                <key>pos</key>
                <string>{1819.00,233.00}</string>
                <key>offset</key>
                <string>{0.00,0.00}</string>
                <key>size</key>
                <string>{32.00,32.00}</string>
                <key>sourceSize</key>
                <string>{32.00,32.00}</string>
                <key>sourceRect</key>
                <string>{{0.00,0.00},{32.00,32.00}}</string>
            </dict>
            <dict>
                <key>id</key>
                <string>1323</string>
                <key>className</key>
                <string>PTModelSprite</string>
                <key>Name</key>
                <dict>
                    <key>value</key>
                    <string>coin action</string>
                </dict>
                <key>pos</key>
                <string>{2044.00,0.00}</string>
                <key>offset</key>
                <string>{30.00,30.00}</string>
                <key>size</key>
                <string>{0.00,0.00}</string>
                <key>sourceSize</key>
                <string>{30.00,30.00}</string>
                <key>sourceRect</key>
                <string>{{30.00,30.00},{0.00,0.00}}</string>
            </dict>
            <dict>
                <key>id</key>
                <string>1338</string>
                <key>className</key>
                <string>PTModelSprite</string>
                <key>Name</key>
                <dict>
                    <key>value</key>
                    <string>coin action</string>
                </dict>
                <key>pos</key>
                <string>{2040.00,0.00}</string>
                <key>offset</key>
                <string>{30.00,30.00}</string>
                <key>size</key>
                <string>{0.00,0.00}</string>
                <key>sourceSize</key>
                <string>{30.00,30.00}</string>
                <key>sourceRect</key>
                <string>{{30.00,30.00},{0.00,0.00}}</string>
            </dict>
            <dict>
                <key>id</key>
                <string>1350</string>
                <key>className</key>
                <string>PTModelSprite</string>
                <key>Name</key>
                <dict>
                    <key>value</key>
                    <string>player</string>
                </dict>
                <key>pos</key>
                <string>{1855.00,233.00}</string>
                <key>offset</key>
                <string>{0.00,0.00}</string>
                <key>size</key>
                <string>{30.00,30.00}</string>
                <key>sourceSize</key>
                <string>{30.00,30.00}</string>
                <key>sourceRect</key>
                <string>{{0.00,0.00},{30.00,30.00}}</string>
            </dict>
            <dict>
                <key>id</key>
                <string>1537</string>
                <key>className</key>
                <string>PTModelSprite</string>
                <key>Name</key>
                <dict>
                    <key>value</key>
                    <string>avatar_629c47e86c3e_128</string>
                </dict>
                <key>pos</key>
                <string>{1632.00,0.00}</string>
                <key>offset</key>
                <string>{0.00,0.00}</string>
                <key>size</key>
                <string>{128.00,128.00}</string>
                <key>sourceSize</key>
                <string>{128.00,128.00}</string>
                <key>sourceRect</key>
                <string>{{0.00,0.00},{128.00,128.00}}</string>
            </dict>
            <dict>
                <key>id</key>
                <string>2686</string>
                <key>className</key>
                <string>PTModelSprite</string>
                <key>Name</key>
                <dict>
                    <key>value</key>
                    <string>white-square</string>
                </dict>
                <key>pos</key>
                <string>{516.00,1019.00}</string>
                <key>offset</key>
                <string>{0.00,0.00}</string>
                <key>size</key>
                <string>{550.00,475.00}</string>
                <key>sourceSize</key>
                <string>{550.00,475.00}</string>
                <key>sourceRect</key>
                <string>{{0.00,0.00},{550.00,475.00}}</string>
            </dict>
            <dict>
                <key>id</key>
                <string>3057</string>
                <key>className</key>
                <string>PTModelSprite</string>
                <key>Name</key>
                <dict>
                    <key>value</key>
                    <string>white-square</string>
                </dict>
                <key>pos</key>
                <string>{1070.00,1019.00}</string>
                <key>offset</key>
                <string>{0.00,0.00}</string>
                <key>size</key>
                <string>{550.00,475.00}</string>
                <key>sourceSize</key>
                <string>{550.00,475.00}</string>
                <key>sourceRect</key>
                <string>{{0.00,0.00},{550.00,475.00}}</string>
            </dict>
            <dict>
                <key>id</key>
                <string>3072</string>
                <key>className</key>
                <string>PTModelSprite</string>
                <key>Name</key>
                <dict>
                    <key>value</key>
                    <string>background</string>
                </dict>
                <key>pos</key>
                <string>{2012.00,132.00}</string>
                <key>offset</key>
                <string>{0.00,0.00}</string>
                <key>size</key>
                <string>{32.00,32.00}</string>
                <key>sourceSize</key>
                <string>{32.00,32.00}</string>
                <key>sourceRect</key>
                <string>{{0.00,0.00},{32.00,32.00}}</string>
            </dict>
            <dict>
                <key>id</key>
                <string>3896</string>
                <key>className</key>
                <string>PTModelSprite</string>
                <key>Name</key>
                <dict>
                    <key>value</key>
                    <string>white-square</string>
                </dict>
                <key>pos</key>
                <string>{0.00,1535.00}</string>
                <key>offset</key>
                <string>{0.00,0.00}</string>
                <key>size</key>
                <string>{550.00,475.00}</string>
                <key>sourceSize</key>
                <string>{550.00,475.00}</string>
                <key>sourceRect</key>
                <string>{{0.00,0.00},{550.00,475.00}}</string>
            </dict>
            <dict>
                <key>id</key>
                <string>3935</string>
                <key>className</key>
                <string>PTModelSprite</string>
                <key>Name</key>
                <dict>
                    <key>value</key>
                    <string>black-square-rounded-corners-hi</string>
                </dict>
                <key>pos</key>
                <string>{1028.00,0.00}</string>
                <key>offset</key>
                <string>{0.00,0.00}</string>
                <key>size</key>
                <string>{600.00,600.00}</string>
                <key>sourceSize</key>
                <string>{600.00,600.00}</string>
                <key>sourceRect</key>
                <string>{{0.00,0.00},{600.00,600.00}}</string>
            </dict>
            <dict>
                <key>id</key>
                <string>3941</string>
                <key>className</key>
                <string>PTModelSprite</string>
                <key>Name</key>
                <dict>
                    <key>value</key>
                    <string>4544827697_6f73866999_b</string>
                </dict>
                <key>pos</key>
                <string>{0.00,0.00}</string>
                <key>offset</key>
                <string>{0.00,0.00}</string>
                <key>size</key>
                <string>{1024.00,1015.00}</string>
                <key>sourceSize</key>
                <string>{1024.00,1015.00}</string>
                <key>sourceRect</key>
                <string>{{0.00,0.00},{1024.00,1015.00}}</string>
            </dict>
            <dict>
                <key>id</key>
                <string>3966</string>
                <key>className</key>
                <string>PTModelSprite</string>
                <key>Name</key>
                <dict>
                    <key>value</key>
                    <string>4544827697_6f73866999_b</string>
                </dict>
                <key>pos</key>
                <string>{0.00,1019.00}</string>
                <key>offset</key>
                <string>{0.00,0.00}</string>
                <key>size</key>
                <string>{1024.00,1015.00}</string>
                <key>sourceSize</key>
                <string>{1024.00,1015.00}</string>
                <key>sourceRect</key>
                <string>{{0.00,0.00},{1024.00,1015.00}}</string>
            </dict>
            <dict>
                <key>id</key>
                <string>4144</string>
                <key>className</key>
                <string>PTModelSprite</string>
                <key>Name</key>
                <dict>
                    <key>value</key>
                    <string>white-square</string>
                </dict>
                <key>pos</key>
                <string>{554.00,1535.00}</string>
                <key>offset</key>
                <string>{0.00,0.00}</string>
                <key>size</key>
                <string>{550.00,475.00}</string>
                <key>sourceSize</key>
                <string>{550.00,475.00}</string>
                <key>sourceRect</key>
                <string>{{0.00,0.00},{550.00,475.00}}</string>
            </dict>
            <dict>
                <key>id</key>
                <string>4207</string>
                <key>className</key>
                <string>PTModelSprite</string>
                <key>Name</key>
                <dict>
                    <key>value</key>
                    <string>white-square</string>
                </dict>
                <key>pos</key>
                <string>{1108.00,1535.00}</string>
                <key>offset</key>
                <string>{0.00,0.00}</string>
                <key>size</key>
                <string>{550.00,475.00}</string>
                <key>sourceSize</key>
                <string>{550.00,475.00}</string>
                <key>sourceRect</key>
                <string>{{0.00,0.00},{550.00,475.00}}</string>
            </dict>
            <dict>
                <key>id</key>
                <string>4861</string>
                <key>className</key>
                <string>PTModelSprite</string>
                <key>Name</key>
                <dict>
                    <key>value</key>
                    <string>white-square</string>
                </dict>
                <key>pos</key>
                <string>{1028.00,1498.00}</string>
                <key>offset</key>
                <string>{0.00,0.00}</string>
                <key>size</key>
                <string>{550.00,475.00}</string>
                <key>sourceSize</key>
                <string>{550.00,475.00}</string>
                <key>sourceRect</key>
                <string>{{0.00,0.00},{550.00,475.00}}</string>
            </dict>
            <dict>
                <key>id</key>
                <string>4866</string>
                <key>className</key>
                <string>PTModelSprite</string>
                <key>Name</key>
                <dict>
                    <key>value</key>
                    <string>avatar_629c47e86c3e_128</string>
                </dict>
                <key>pos</key>
                <string>{1764.00,0.00}</string>
                <key>offset</key>
                <string>{0.00,0.00}</string>
                <key>size</key>
                <string>{128.00,128.00}</string>
                <key>sourceSize</key>
                <string>{128.00,128.00}</string>
                <key>sourceRect</key>
                <string>{{0.00,0.00},{128.00,128.00}}</string>
            </dict>
            <dict>
                <key>id</key>
                <string>4937</string>
                <key>className</key>
                <string>PTModelSprite</string>
                <key>Name</key>
                <dict>
                    <key>value</key>
                    <string>white-square</string>
                </dict>
                <key>pos</key>
                <string>{1028.00,1019.00}</string>
                <key>offset</key>
                <string>{0.00,0.00}</string>
                <key>size</key>
                <string>{550.00,475.00}</string>
                <key>sourceSize</key>
                <string>{550.00,475.00}</string>
                <key>sourceRect</key>
                <string>{{0.00,0.00},{550.00,475.00}}</string>
            </dict>
            <dict>
                <key>id</key>
                <string>4996</string>
                <key>className</key>
                <string>PTModelSprite</string>
                <key>Name</key>
                <dict>
                    <key>value</key>
                    <string>4544827697_6f73866999_b</string>
                </dict>
                <key>pos</key>
                <string>{0.00,0.00}</string>
                <key>offset</key>
                <string>{0.00,0.00}</string>
                <key>size</key>
                <string>{1024.00,1015.00}</string>
                <key>sourceSize</key>
                <string>{1024.00,1015.00}</string>
                <key>sourceRect</key>
                <string>{{0.00,0.00},{1024.00,1015.00}}</string>
            </dict>
            <dict>
                <key>id</key>
                <string>5038</string>
                <key>className</key>
                <string>PTModelSprite</string>
                <key>Name</key>
                <dict>
                    <key>value</key>
                    <string>musicOff</string>
                </dict>
                <key>pos</key>
                <string>{1632.00,233.00}</string>
                <key>offset</key>
                <string>{22.00,22.00}</string>
                <key>size</key>
                <string>{60.00,62.00}</string>
                <key>sourceSize</key>
                <string>{100.00,100.00}</string>
                <key>sourceRect</key>
                <string>{{22.00,22.00},{60.00,62.00}}</string>
            </dict>
            <dict>
                <key>id</key>
                <string>5043</string>
                <key>className</key>
                <string>PTModelSprite</string>
                <key>Name</key>
                <dict>
                    <key>value</key>
                    <string>musicOn</string>
                </dict>
                <key>pos</key>
                <string>{1953.00,132.00}</string>
                <key>offset</key>
                <string>{22.00,22.00}</string>
                <key>size</key>
                <string>{55.00,62.00}</string>
                <key>sourceSize</key>
                <string>{100.00,100.00}</string>
                <key>sourceRect</key>
                <string>{{22.00,22.00},{55.00,62.00}}</string>
            </dict>
            <dict>
                <key>id</key>
                <string>5049</string>
                <key>className</key>
                <string>PTModelSprite</string>
                <key>Name</key>
                <dict>
                    <key>value</key>
                    <string>information</string>
                </dict>
                <key>pos</key>
                <string>{2000.00,0.00}</string>
                <key>offset</key>
                <string>{34.00,18.00}</string>
                <key>size</key>
                <string>{36.00,68.00}</string>
                <key>sourceSize</key>
                <string>{100.00,100.00}</string>
                <key>sourceRect</key>
                <string>{{34.00,18.00},{36.00,68.00}}</string>
            </dict>
            <dict>
                <key>id</key>
                <string>5066</string>
                <key>className</key>
                <string>PTModelSprite</string>
                <key>Name</key>
                <dict>
                    <key>value</key>
                    <string>cross</string>
                </dict>
                <key>pos</key>
                <string>{1885.00,132.00}</string>
                <key>offset</key>
                <string>{18.00,20.00}</string>
                <key>size</key>
                <string>{64.00,64.00}</string>
                <key>sourceSize</key>
                <string>{100.00,100.00}</string>
                <key>sourceRect</key>
                <string>{{18.00,20.00},{64.00,64.00}}</string>
            </dict>
            <dict>
                <key>id</key>
                <string>5080</string>
                <key>className</key>
                <string>PTModelSprite</string>
                <key>Name</key>
                <dict>
                    <key>value</key>
                    <string>pause</string>
                </dict>
                <key>pos</key>
                <string>{1825.00,132.00}</string>
                <key>offset</key>
                <string>{22.00,16.00}</string>
                <key>size</key>
                <string>{56.00,65.00}</string>
                <key>sourceSize</key>
                <string>{100.00,100.00}</string>
                <key>sourceRect</key>
                <string>{{22.00,16.00},{56.00,65.00}}</string>
            </dict>
            <dict>
                <key>id</key>
                <string>5093</string>
                <key>className</key>
                <string>PTModelSprite</string>
                <key>Name</key>
                <dict>
                    <key>value</key>
                    <string>white-square</string>
                </dict>
                <key>pos</key>
                <string>{1028.00,479.00}</string>
                <key>offset</key>
                <string>{0.00,0.00}</string>
                <key>size</key>
                <string>{550.00,475.00}</string>
                <key>sourceSize</key>
                <string>{550.00,475.00}</string>
                <key>sourceRect</key>
                <string>{{0.00,0.00},{550.00,475.00}}</string>
            </dict>
            <dict>
                <key>id</key>
                <string>5098</string>
                <key>className</key>
                <string>PTModelSprite</string>
                <key>Name</key>
                <dict>
                    <key>value</key>
                    <string>musicOff</string>
                </dict>
                <key>pos</key>
                <string>{1696.00,233.00}</string>
                <key>offset</key>
                <string>{22.00,22.00}</string>
                <key>size</key>
                <string>{60.00,62.00}</string>
                <key>sourceSize</key>
                <string>{100.00,100.00}</string>
                <key>sourceRect</key>
                <string>{{22.00,22.00},{60.00,62.00}}</string>
            </dict>
            <dict>
                <key>id</key>
                <string>5103</string>
                <key>className</key>
                <string>PTModelSprite</string>
                <key>Name</key>
                <dict>
                    <key>value</key>
                    <string>musicOn</string>
                </dict>
                <key>pos</key>
                <string>{1760.00,233.00}</string>
                <key>offset</key>
                <string>{22.00,22.00}</string>
                <key>size</key>
                <string>{55.00,62.00}</string>
                <key>sourceSize</key>
                <string>{100.00,100.00}</string>
                <key>sourceRect</key>
                <string>{{22.00,22.00},{55.00,62.00}}</string>
            </dict>
            <dict>
                <key>id</key>
                <string>5108</string>
                <key>className</key>
                <string>PTModelSprite</string>
                <key>Name</key>
                <dict>
                    <key>value</key>
                    <string>4544827697_6f73866999_b</string>
                </dict>
                <key>pos</key>
                <string>{0.00,1019.00}</string>
                <key>offset</key>
                <string>{0.00,0.00}</string>
                <key>size</key>
                <string>{1024.00,1015.00}</string>
                <key>sourceSize</key>
                <string>{1024.00,1015.00}</string>
                <key>sourceRect</key>
                <string>{{0.00,0.00},{1024.00,1015.00}}</string>
            </dict>
            <dict>
                <key>id</key>
                <string>5291</string>
                <key>className</key>
                <string>PTModelSprite</string>
                <key>Name</key>
                <dict>
                    <key>value</key>
                    <string>4544827697_6f73866999_b</string>
                </dict>
                <key>pos</key>
                <string>{0.00,0.00}</string>
                <key>offset</key>
                <string>{0.00,0.00}</string>
                <key>size</key>
                <string>{1024.00,1015.00}</string>
                <key>sourceSize</key>
                <string>{1024.00,1015.00}</string>
                <key>sourceRect</key>
                <string>{{0.00,0.00},{1024.00,1015.00}}</string>
            </dict>
            <dict>
                <key>id</key>
                <string>5296</string>
                <key>className</key>
                <string>PTModelSprite</string>
                <key>Name</key>
                <dict>
                    <key>value</key>
                    <string>4544827697_6f73866999_b</string>
                </dict>
                <key>pos</key>
                <string>{0.00,1019.00}</string>
                <key>offset</key>
                <string>{0.00,0.00}</string>
                <key>size</key>
                <string>{1024.00,1015.00}</string>
                <key>sourceSize</key>
                <string>{1024.00,1015.00}</string>
                <key>sourceRect</key>
                <string>{{0.00,0.00},{1024.00,1015.00}}</string>
            </dict>
            <dict>
                <key>id</key>
                <string>6213</string>
                <key>className</key>
                <string>PTModelSprite</string>
                <key>Name</key>
                <dict>
                    <key>value</key>
                    <string>white-square</string>
                </dict>
                <key>pos</key>
                <string>{1028.00,0.00}</string>
                <key>offset</key>
                <string>{0.00,0.00}</string>
                <key>size</key>
                <string>{550.00,475.00}</string>
                <key>sourceSize</key>
                <string>{550.00,475.00}</string>
                <key>sourceRect</key>
                <string>{{0.00,0.00},{550.00,475.00}}</string>
            </dict>
            <dict>
                <key>id</key>
                <string>6219</string>
                <key>className</key>
                <string>PTModelSprite</string>
                <key>Name</key>
                <dict>
                    <key>value</key>
                    <string>4544827697_6f73866999_b</string>
                </dict>
                <key>pos</key>
                <string>{0.00,0.00}</string>
                <key>offset</key>
                <string>{0.00,0.00}</string>
                <key>size</key>
                <string>{1024.00,1015.00}</string>
                <key>sourceSize</key>
                <string>{1024.00,1015.00}</string>
                <key>sourceRect</key>
                <string>{{0.00,0.00},{1024.00,1015.00}}</string>
            </dict>
            <dict>
                <key>id</key>
                <string>6224</string>
                <key>className</key>
                <string>PTModelSprite</string>
                <key>Name</key>
                <dict>
                    <key>value</key>
                    <string>white_button</string>
                </dict>
                <key>pos</key>
                <string>{1028.00,604.00}</string>
                <key>offset</key>
                <string>{0.00,0.00}</string>
                <key>size</key>
                <string>{550.00,95.00}</string>
                <key>sourceSize</key>
                <string>{550.00,95.00}</string>
                <key>sourceRect</key>
                <string>{{0.00,0.00},{550.00,95.00}}</string>
            </dict>
            <dict>
                <key>id</key>
                <string>6230</string>
                <key>className</key>
                <string>PTModelSprite</string>
                <key>Name</key>
                <dict>
                    <key>value</key>
                    <string>white_button</string>
                </dict>
                <key>pos</key>
                <string>{1582.00,604.00}</string>
                <key>offset</key>
                <string>{0.00,0.00}</string>
                <key>size</key>
                <string>{440.00,95.00}</string>
                <key>sourceSize</key>
                <string>{440.00,95.00}</string>
                <key>sourceRect</key>
                <string>{{0.00,0.00},{440.00,95.00}}</string>
            </dict>
            <dict>
                <key>id</key>
                <string>6236</string>
                <key>className</key>
                <string>PTModelSprite</string>
                <key>Name</key>
                <dict>
                    <key>value</key>
                    <string>white_button</string>
                </dict>
                <key>pos</key>
                <string>{1028.00,703.00}</string>
                <key>offset</key>
                <string>{0.00,0.00}</string>
                <key>size</key>
                <string>{484.00,95.00}</string>
                <key>sourceSize</key>
                <string>{484.00,95.00}</string>
                <key>sourceRect</key>
                <string>{{0.00,0.00},{484.00,95.00}}</string>
            </dict>
            <dict>
                <key>id</key>
                <string>6242</string>
                <key>className</key>
                <string>PTModelSprite</string>
                <key>Name</key>
                <dict>
                    <key>value</key>
                    <string>white_button</string>
                </dict>
                <key>pos</key>
                <string>{1516.00,703.00}</string>
                <key>offset</key>
                <string>{0.00,0.00}</string>
                <key>size</key>
                <string>{508.00,95.00}</string>
                <key>sourceSize</key>
                <string>{508.00,95.00}</string>
                <key>sourceRect</key>
                <string>{{0.00,0.00},{508.00,95.00}}</string>
            </dict>
            <dict>
                <key>id</key>
                <string>6248</string>
                <key>className</key>
                <string>PTModelSprite</string>
                <key>Name</key>
                <dict>
                    <key>value</key>
                    <string>white_button</string>
                </dict>
                <key>pos</key>
                <string>{1028.00,802.00}</string>
                <key>offset</key>
                <string>{0.00,0.00}</string>
                <key>size</key>
                <string>{484.00,95.00}</string>
                <key>sourceSize</key>
                <string>{484.00,95.00}</string>
                <key>sourceRect</key>
                <string>{{0.00,0.00},{484.00,95.00}}</string>
            </dict>
            <dict>
                <key>id</key>
                <string>6254</string>
                <key>className</key>
                <string>PTModelSprite</string>
                <key>Name</key>
                <dict>
                    <key>value</key>
                    <string>white_button</string>
                </dict>
                <key>pos</key>
                <string>{1516.00,802.00}</string>
                <key>offset</key>
                <string>{0.00,0.00}</string>
                <key>size</key>
                <string>{484.00,95.00}</string>
                <key>sourceSize</key>
                <string>{484.00,95.00}</string>
                <key>sourceRect</key>
                <string>{{0.00,0.00},{484.00,95.00}}</string>
            </dict>
            <dict>
                <key>id</key>
                <string>6260</string>
                <key>className</key>
                <string>PTModelSprite</string>
                <key>Name</key>
                <dict>
                    <key>value</key>
                    <string>white_button</string>
                </dict>
                <key>pos</key>
                <string>{1028.00,901.00}</string>
                <key>offset</key>
                <string>{0.00,0.00}</string>
                <key>size</key>
                <string>{484.00,95.00}</string>
                <key>sourceSize</key>
                <string>{484.00,95.00}</string>
                <key>sourceRect</key>
                <string>{{0.00,0.00},{484.00,95.00}}</string>
            </dict>
            <dict>
                <key>id</key>
                <string>6269</string>
                <key>className</key>
                <string>PTModelSprite</string>
                <key>Name</key>
                <dict>
                    <key>value</key>
                    <string>white_button</string>
                </dict>
                <key>pos</key>
                <string>{1516.00,901.00}</string>
                <key>offset</key>
                <string>{0.00,0.00}</string>
                <key>size</key>
                <string>{484.00,95.00}</string>
                <key>sourceSize</key>
                <string>{484.00,95.00}</string>
                <key>sourceRect</key>
                <string>{{0.00,0.00},{484.00,95.00}}</string>
            </dict>
            <dict>
                <key>id</key>
                <string>6345</string>
                <key>className</key>
                <string>PTModelSprite</string>
                <key>Name</key>
                <dict>
                    <key>value</key>
                    <string>white_button</string>
                </dict>
                <key>pos</key>
                <string>{1516.00,1019.00}</string>
                <key>offset</key>
                <string>{0.00,0.00}</string>
                <key>size</key>
                <string>{484.00,95.00}</string>
                <key>sourceSize</key>
                <string>{484.00,95.00}</string>
                <key>sourceRect</key>
                <string>{{0.00,0.00},{484.00,95.00}}</string>
            </dict>
            <dict>
                <key>id</key>
                <string>6351</string>
                <key>className</key>
                <string>PTModelSprite</string>
                <key>Name</key>
                <dict>
                    <key>value</key>
                    <string>white_button</string>
                </dict>
                <key>pos</key>
                <string>{1028.00,1019.00}</string>
                <key>offset</key>
                <string>{0.00,0.00}</string>
                <key>size</key>
                <string>{484.00,95.00}</string>
                <key>sourceSize</key>
                <string>{484.00,95.00}</string>
                <key>sourceRect</key>
                <string>{{0.00,0.00},{484.00,95.00}}</string>
            </dict>
            <dict>
                <key>id</key>
                <string>6357</string>
                <key>className</key>
                <string>PTModelSprite</string>
                <key>Name</key>
                <dict>
                    <key>value</key>
                    <string>4544827697_6f73866999_b</string>
                </dict>
                <key>pos</key>
                <string>{0.00,1019.00}</string>
                <key>offset</key>
                <string>{0.00,0.00}</string>
                <key>size</key>
                <string>{1024.00,1015.00}</string>
                <key>sourceSize</key>
                <string>{1024.00,1015.00}</string>
                <key>sourceRect</key>
                <string>{{0.00,0.00},{1024.00,1015.00}}</string>
            </dict>
            <dict>
                <key>id</key>
                <string>6382</string>
                <key>className</key>
                <string>PTModelSprite</string>
                <key>Name</key>
                <dict>
                    <key>value</key>
                    <string>white_button</string>
                </dict>
                <key>pos</key>
                <string>{1516.00,875.00}</string>
                <key>offset</key>
                <string>{0.00,0.00}</string>
                <key>size</key>
                <string>{484.00,95.00}</string>
                <key>sourceSize</key>
                <string>{484.00,95.00}</string>
                <key>sourceRect</key>
                <string>{{0.00,0.00},{484.00,95.00}}</string>
            </dict>
            <dict>
                <key>id</key>
                <string>6481</string>
                <key>className</key>
                <string>PTModelSprite</string>
                <key>Name</key>
                <dict>
                    <key>value</key>
                    <string>remove_ads</string>
                </dict>
                <key>pos</key>
                <string>{1028.00,875.00}</string>
                <key>offset</key>
                <string>{0.00,0.00}</string>
                <key>size</key>
                <string>{484.00,95.00}</string>
                <key>sourceSize</key>
                <string>{484.00,95.00}</string>
                <key>sourceRect</key>
                <string>{{0.00,0.00},{484.00,95.00}}</string>
            </dict>
            <dict>
                <key>id</key>
                <string>6516</string>
                <key>className</key>
                <string>PTModelSprite</string>
                <key>Name</key>
                <dict>
                    <key>value</key>
                    <string>remove_ads</string>
                </dict>
                <key>pos</key>
                <string>{1516.00,776.00}</string>
                <key>offset</key>
                <string>{0.00,0.00}</string>
                <key>size</key>
                <string>{484.00,95.00}</string>
                <key>sourceSize</key>
                <string>{484.00,95.00}</string>
                <key>sourceRect</key>
                <string>{{0.00,0.00},{484.00,95.00}}</string>
            </dict>
            <dict>
                <key>id</key>
                <string>6544</string>
                <key>className</key>
                <string>PTModelSprite</string>
                <key>Name</key>
                <dict>
                    <key>value</key>
                    <string>white_button</string>
                </dict>
                <key>pos</key>
                <string>{1028.00,776.00}</string>
                <key>offset</key>
                <string>{0.00,0.00}</string>
                <key>size</key>
                <string>{484.00,95.00}</string>
                <key>sourceSize</key>
                <string>{484.00,95.00}</string>
                <key>sourceRect</key>
                <string>{{0.00,0.00},{484.00,95.00}}</string>
            </dict>
            <dict>
                <key>id</key>
                <string>6550</string>
                <key>className</key>
                <string>PTModelSprite</string>
                <key>Name</key>
                <dict>
                    <key>value</key>
                    <string>4544827697_6f73866999_b</string>
                </dict>
                <key>pos</key>
                <string>{0.00,0.00}</string>
                <key>offset</key>
                <string>{0.00,0.00}</string>
                <key>size</key>
                <string>{1024.00,1015.00}</string>
                <key>sourceSize</key>
                <string>{1024.00,1015.00}</string>
                <key>sourceRect</key>
                <string>{{0.00,0.00},{1024.00,1015.00}}</string>
            </dict>
            <dict>
                <key>id</key>
                <string>6606</string>
                <key>className</key>
                <string>PTModelSprite</string>
                <key>Name</key>
                <dict>
                    <key>value</key>
                    <string>remove_ads</string>
                </dict>
                <key>pos</key>
                <string>{1516.00,677.00}</string>
                <key>offset</key>
                <string>{0.00,0.00}</string>
                <key>size</key>
                <string>{484.00,95.00}</string>
                <key>sourceSize</key>
                <string>{484.00,95.00}</string>
                <key>sourceRect</key>
                <string>{{0.00,0.00},{484.00,95.00}}</string>
            </dict>
            <dict>
                <key>id</key>
                <string>6612</string>
                <key>className</key>
                <string>PTModelSprite</string>
                <key>Name</key>
                <dict>
                    <key>value</key>
                    <string>white_button</string>
                </dict>
                <key>pos</key>
                <string>{1028.00,677.00}</string>
                <key>offset</key>
                <string>{0.00,0.00}</string>
                <key>size</key>
                <string>{484.00,95.00}</string>
                <key>sourceSize</key>
                <string>{484.00,95.00}</string>
                <key>sourceRect</key>
                <string>{{0.00,0.00},{484.00,95.00}}</string>
            </dict>
            <dict>
                <key>id</key>
                <string>6618</string>
                <key>className</key>
                <string>PTModelSprite</string>
                <key>Name</key>
                <dict>
                    <key>value</key>
                    <string>4544827697_6f73866999_b</string>
                </dict>
                <key>pos</key>
                <string>{0.00,0.00}</string>
                <key>offset</key>
                <string>{0.00,0.00}</string>
                <key>size</key>
                <string>{1024.00,1015.00}</string>
                <key>sourceSize</key>
                <string>{1024.00,1015.00}</string>
                <key>sourceRect</key>
                <string>{{0.00,0.00},{1024.00,1015.00}}</string>
            </dict>
            <dict>
                <key>id</key>
                <string>6675</string>
                <key>className</key>
                <string>PTModelSprite</string>
                <key>Name</key>
                <dict>
                    <key>value</key>
                    <string>white_button</string>
                </dict>
                <key>pos</key>
                <string>{1516.00,578.00}</string>
                <key>offset</key>
                <string>{0.00,0.00}</string>
                <key>size</key>
                <string>{484.00,95.00}</string>
                <key>sourceSize</key>
                <string>{484.00,95.00}</string>
                <key>sourceRect</key>
                <string>{{0.00,0.00},{484.00,95.00}}</string>
            </dict>
            <dict>
                <key>id</key>
                <string>6778</string>
                <key>className</key>
                <string>PTModelSprite</string>
                <key>Name</key>
                <dict>
                    <key>value</key>
                    <string>remove_ads</string>
                </dict>
                <key>pos</key>
                <string>{1028.00,578.00}</string>
                <key>offset</key>
                <string>{0.00,0.00}</string>
                <key>size</key>
                <string>{484.00,95.00}</string>
                <key>sourceSize</key>
                <string>{484.00,95.00}</string>
                <key>sourceRect</key>
                <string>{{0.00,0.00},{484.00,95.00}}</string>
            </dict>
            <dict>
                <key>id</key>
                <string>8137</string>
                <key>className</key>
                <string>PTModelSprite</string>
                <key>Name</key>
                <dict>
                    <key>value</key>
                    <string>move</string>
                </dict>
                <key>pos</key>
                <string>{1028.00,1118.00}</string>
                <key>offset</key>
                <string>{25.00,370.00}</string>
                <key>size</key>
                <string>{569.00,59.00}</string>
                <key>sourceSize</key>
                <string>{640.00,800.00}</string>
                <key>sourceRect</key>
                <string>{{25.00,370.00},{569.00,59.00}}</string>
            </dict>
            <dict>
                <key>id</key>
                <string>8145</string>
                <key>className</key>
                <string>PTModelSprite</string>
                <key>Name</key>
                <dict>
                    <key>value</key>
                    <string>contrast_icon</string>
                </dict>
                <key>pos</key>
                <string>{0.00,0.00}</string>
                <key>offset</key>
                <string>{0.00,0.00}</string>
                <key>size</key>
                <string>{0.00,0.00}</string>
                <key>sourceSize</key>
                <string>{512.00,512.00}</string>
                <key>sourceRect</key>
                <string>{{0.00,0.00},{0.00,0.00}}</string>
            </dict>
            <dict>
                <key>id</key>
                <string>8200</string>
                <key>className</key>
                <string>PTModelSprite</string>
                <key>Name</key>
                <dict>
                    <key>value</key>
                    <string>white-square</string>
                </dict>
                <key>pos</key>
                <string>{1028.00,0.00}</string>
                <key>offset</key>
                <string>{0.00,0.00}</string>
                <key>size</key>
                <string>{550.00,475.00}</string>
                <key>sourceSize</key>
                <string>{550.00,475.00}</string>
                <key>sourceRect</key>
                <string>{{0.00,0.00},{550.00,475.00}}</string>
            </dict>
            <dict>
                <key>id</key>
                <string>8226</string>
                <key>className</key>
                <string>PTModelSprite</string>
                <key>Name</key>
                <dict>
                    <key>value</key>
                    <string>contrast_icon</string>
                </dict>
                <key>pos</key>
                <string>{0.00,0.00}</string>
                <key>offset</key>
                <string>{0.00,0.00}</string>
                <key>size</key>
                <string>{0.00,0.00}</string>
                <key>sourceSize</key>
                <string>{512.00,512.00}</string>
                <key>sourceRect</key>
                <string>{{0.00,0.00},{0.00,0.00}}</string>
            </dict>
            <dict>
                <key>id</key>
                <string>8234</string>
                <key>className</key>
                <string>PTModelSprite</string>
                <key>Name</key>
                <dict>
                    <key>value</key>
                    <string>contrast_icon</string>
                </dict>
                <key>pos</key>
                <string>{0.00,0.00}</string>
                <key>offset</key>
                <string>{0.00,0.00}</string>
                <key>size</key>
                <string>{0.00,0.00}</string>
                <key>sourceSize</key>
                <string>{512.00,512.00}</string>
                <key>sourceRect</key>
                <string>{{0.00,0.00},{0.00,0.00}}</string>
            </dict>
            <dict>
                <key>id</key>
                <string>8241</string>
                <key>className</key>
                <string>PTModelSprite</string>
                <key>Name</key>
                <dict>
                    <key>value</key>
                    <string>leaderboardsSimple</string>
                </dict>
                <key>pos</key>
                <string>{1950.00,0.00}</string>
                <key>offset</key>
                <string>{12.00,36.00}</string>
                <key>size</key>
                <string>{72.00,48.00}</string>
                <key>sourceSize</key>
                <string>{100.00,100.00}</string>
                <key>sourceRect</key>
                <string>{{12.00,36.00},{72.00,48.00}}</string>
            </dict>
            <dict>
                <key>id</key>
                <string>8245</string>
                <key>className</key>
                <string>PTModelSprite</string>
                <key>Name</key>
                <dict>
                    <key>value</key>
                    <string>leaderboardsSimple</string>
                </dict>
                <key>pos</key>
                <string>{1874.00,0.00}</string>
                <key>offset</key>
                <string>{12.00,36.00}</string>
                <key>size</key>
                <string>{72.00,48.00}</string>
                <key>sourceSize</key>
                <string>{100.00,100.00}</string>
                <key>sourceRect</key>
                <string>{{12.00,36.00},{72.00,48.00}}</string>
            </dict>
            <dict>
                <key>id</key>
                <string>8251</string>
                <key>className</key>
                <string>PTModelSprite</string>
                <key>Name</key>
                <dict>
                    <key>value</key>
                    <string>leaderboardsComplex</string>
                </dict>
                <key>pos</key>
                <string>{1726.00,0.00}</string>
                <key>offset</key>
                <string>{18.00,26.00}</string>
                <key>size</key>
                <string>{68.00,56.00}</string>
                <key>sourceSize</key>
                <string>{100.00,100.00}</string>
                <key>sourceRect</key>
                <string>{{18.00,26.00},{68.00,56.00}}</string>
            </dict>
            <dict>
                <key>id</key>
                <string>8257</string>
                <key>className</key>
                <string>PTModelSprite</string>
                <key>Name</key>
                <dict>
                    <key>value</key>
                    <string>leaderboardsSimple</string>
                </dict>
                <key>pos</key>
                <string>{1798.00,0.00}</string>
                <key>offset</key>
                <string>{12.00,36.00}</string>
                <key>size</key>
                <string>{72.00,48.00}</string>
                <key>sourceSize</key>
                <string>{100.00,100.00}</string>
                <key>sourceRect</key>
                <string>{{12.00,36.00},{72.00,48.00}}</string>
            </dict>
            <dict>
                <key>id</key>
                <string>8263</string>
                <key>className</key>
                <string>PTModelSprite</string>
                <key>Name</key>
                <dict>
                    <key>value</key>
                    <string>leaderboardsComplex</string>
                </dict>
                <key>pos</key>
                <string>{1654.00,0.00}</string>
                <key>offset</key>
                <string>{18.00,26.00}</string>
                <key>size</key>
                <string>{68.00,56.00}</string>
                <key>sourceSize</key>
                <string>{100.00,100.00}</string>
                <key>sourceRect</key>
                <string>{{18.00,26.00},{68.00,56.00}}</string>
            </dict>
            <dict>
                <key>id</key>
                <string>8868</string>
                <key>className</key>
                <string>PTModelSprite</string>
                <key>Name</key>
                <dict>
                    <key>value</key>
                    <string>remove_ads_button</string>
                </dict>
                <key>pos</key>
                <string>{1516.00,479.00}</string>
                <key>offset</key>
                <string>{0.00,0.00}</string>
                <key>size</key>
                <string>{484.00,95.00}</string>
                <key>sourceSize</key>
                <string>{484.00,95.00}</string>
                <key>sourceRect</key>
                <string>{{0.00,0.00},{484.00,95.00}}</string>
            </dict>
            <dict>
                <key>id</key>
                <string>8896</string>
                <key>className</key>
                <string>PTModelSprite</string>
                <key>Name</key>
                <dict>
                    <key>value</key>
                    <string>remove_ads_button</string>
                </dict>
                <key>pos</key>
                <string>{1028.00,479.00}</string>
                <key>offset</key>
                <string>{0.00,0.00}</string>
                <key>size</key>
                <string>{484.00,95.00}</string>
                <key>sourceSize</key>
                <string>{484.00,95.00}</string>
                <key>sourceRect</key>
                <string>{{0.00,0.00},{484.00,95.00}}</string>
            </dict>
            <dict>
                <key>id</key>
                <string>9170</string>
                <key>className</key>
                <string>PTModelSprite</string>
                <key>Name</key>
                <dict>
                    <key>value</key>
                    <string>leaderboardsComplex copy</string>
                </dict>
                <key>pos</key>
                <string>{1582.00,0.00}</string>
                <key>offset</key>
                <string>{18.00,26.00}</string>
                <key>size</key>
                <string>{68.00,56.00}</string>
                <key>sourceSize</key>
                <string>{100.00,100.00}</string>
                <key>sourceRect</key>
                <string>{{18.00,26.00},{68.00,56.00}}</string>
            </dict>
        </array>
    </dict>
</plist>
